mkhwgen/__init__.py
mkhwgen-0.0.8.dist-info/METADATA
mkhwgen-0.0.8.dist-info/WHEEL
mkhwgen-0.0.8.dist-info/top_level.txt
mkhwgen-0.0.8.dist-info/RECORD
