Metadata-Version: 2.1
Name: mkhwgen
Version: 0.0.8
Summary: Weather Generator
Home-page: https://gitlab.com/dogbull/mkhwgen
Author: ParkJooHyeon
Author-email: www.jrr.kr@gmail.com
License: UNKNOWN
Keywords: weather,generator
Platform: UNKNOWN
Classifier: Programming Language :: Python :: 3
Classifier: Programming Language :: Python :: 3.2
Classifier: Programming Language :: Python :: 3.3
Classifier: Programming Language :: Python :: 3.4
Classifier: Programming Language :: Python :: 3.5
Classifier: Programming Language :: Python :: 3.6
Classifier: Programming Language :: Python :: 3.8
Classifier: Programming Language :: Python :: 3.9
Classifier: Programming Language :: Python :: 3.10
Requires-Python: >=3
Requires-Dist: numpy
Requires-Dist: pandas
Requires-Dist: python-dateutil
